ksycopg2/__init__.py
ksycopg2/_ipaddress.py
ksycopg2/_json.py
ksycopg2/_ksycopg.cpython-38-aarch64-linux-gnu.so
ksycopg2/_lru_cache.py
ksycopg2/_range.py
ksycopg2/compat.py
ksycopg2/errorcodes.py
ksycopg2/errors.py
ksycopg2/extensions.py
ksycopg2/extras.py
ksycopg2/libkci.so.5
ksycopg2/pool.py
ksycopg2/sql.py
ksycopg2/tz.py
ksycopg2/__pycache__/__init__.cpython-38.pyc
ksycopg2/__pycache__/_json.cpython-38.pyc
ksycopg2/__pycache__/_range.cpython-38.pyc
ksycopg2/__pycache__/compat.cpython-38.pyc
ksycopg2/__pycache__/errors.cpython-38.pyc
ksycopg2/__pycache__/extensions.cpython-38.pyc
ksycopg2/__pycache__/tz.cpython-38.pyc
ksycopg2-2.9.0.dist-info/LICENSE
ksycopg2-2.9.0.dist-info/METADATA
ksycopg2-2.9.0.dist-info/WHEEL
ksycopg2-2.9.0.dist-info/top_level.txt
ksycopg2-2.9.0.dist-info/RECORD
